{
    "Rat":{
        "name":"Rat",
        "kind":1,
        "shadowOffsetY":-2,
        "isAggressive":false,
        "hpPerLevel":40,
        "armor":1,
        "weapon":1,
        "minLevel":1,
        "maxLevel":10
    },
    "Snek":{
        "name":"Snake",
        "kind":2,
        "atkSpeed":40,
        "shadowOffsetY":-4,
        "hpPerLevel":30,
        "armor":1,
        "weapon":1,
        "minLevel":11,
        "maxLevel":20
    },
    "Goblin":{
        "name":"Goblin",
        "kind":3,
        "atkSpeed":600,
        "attackRate":700,
        "hpPerLevel":25,
        "armor":1,
        "weapon":1,
        "minLevel":15,
        "maxLevel":25,
        "isSpeech":1
    },
    "Orc":{
        "kind":4,
        "hpPerLevel":30,
        "armor":1,
        "weapon":1,
        "minLevel":21,
        "maxLevel":30,
        "isSpeech":1
    },
    "Skeleton":{
        "kind":5,
        "shadowOffsetY":1,
        "attackRate":1300,
        "hpPerLevel":30,
        "armor":1,
        "weapon":1,
        "minLevel":25,
        "maxLevel":35
    },
    "Wizard":{
        "kind":6,
        "hpPerLevel":50,
        "armor":1,
        "weapon":1,
        "type":1,
        "minLevel":31,
        "maxLevel":40,
        "isSpeech":1
    },
    "Ogre":{
        "kind":7,
        "hpPerLevel":30,
        "armor":1,
        "weapon":1,
        "minLevel":35,
        "maxLevel":45,
        "isSpeech":1
    },
    "OldOgre":{
        "kind":8,
        "hpPerLevel":30,
        "armor":1,
        "weapon":1,
        "minLevel":41,
        "maxLevel":50,
        "isSpeech":1
    },
    "Crab":{
        "kind":9,
        "hpPerLevel":30,
        "armor":1,
        "weapon":1,
        "minLevel":45,
        "maxLevel":55
    },
    "Bat":{
        "kind":10,
        "hpPerLevel":30,
        "armor":1,
        "weapon":1,
        "minLevel":51,
        "maxLevel":60
    },
    "Skeleton2":{
        "kind":11,
        "hpPerLevel":30,
        "armor":1,
        "weapon":1,
        "minLevel":55,
        "maxLevel":65
    },
    "Hobgoblin":{
        "kind":12,
        "hpPerLevel":30,
        "armor":1,
        "weapon":1,
        "minLevel":61,
        "maxLevel":70,
        "isSpeech":1
    },
    "Eye":{
        "kind":13,
        "hpPerLevel":30,
        "armor":1,
        "weapon":1,
        "minLevel":65,
        "maxLevel":75
    },
    "Spectre":{
        "kind":14,
        "hpPerLevel":30,
        "armor":1,
        "weapon":1,
        "minLevel":71,
        "maxLevel":80
    },
    "DeathKnight":{
        "kind":15,
        "hpPerLevel":30,
        "armor":1,
        "weapon":1,
        "minLevel":75,
        "maxLevel":85,
        "isSpeech":1
    },
    "skeletonking":{
        "name":"Skeleton King",
        "kind":16,
        "isAggressive":true,
        "hpPerLevel":200,
        "minLevel":1,
        "maxLevel":100,
        "spawnChance":1,
        "moveSpeed":750,
        "walkSpeed":750
    }
}
